{"name":"Inscribir aprendices en una ruta de manera exitosa","id":"inscribir-aprendices-a-rutas-de-aprendizaje;inscribir-aprendices-en-una-ruta-de-manera-exitosa","testSteps":[{"number":1,"description":"Example: {learnedId\u003d\"6447512d8cc268d0e07e4d40\", courseId\u003d\"644ab5633204e8c1f59f3215\", status\u003d201}","duration":750,"startTime":"2023-04-27T13:29:14.859-05:00[America/Bogota]","result":"SUCCESS","precondition":false,"level":0,"lineNumber":15,"children":[{"number":2,"description":"Given el administrador desea inscribir un aprendiz a una ruta de aprendizaje","duration":6,"startTime":"2023-04-27T13:29:14.861-05:00[America/Bogota]","result":"SUCCESS","precondition":false,"level":1},{"number":3,"description":"When envia el reto con los datos de  id del aprendiz \"6447512d8cc268d0e07e4d40\" y  id del curso \"644ab5633204e8c1f59f3215\"","duration":729,"startTime":"2023-04-27T13:29:14.870-05:00[America/Bogota]","result":"SUCCESS","precondition":false,"level":1,"children":[{"number":4,"description":"Team2 do post","duration":723,"startTime":"2023-04-27T13:29:14.873-05:00[America/Bogota]","result":"SUCCESS","precondition":false,"level":2,"children":[{"number":5,"description":"team2 executes a POST on the resource learner/subscribeRoute","duration":719,"startTime":"2023-04-27T13:29:14.876-05:00[America/Bogota]","result":"SUCCESS","precondition":false,"level":3,"children":[{"number":6,"description":"POST https://campus-matcafe-backend-sofka-production.up.railway.app/learner/subscribeRoute\r","duration":0,"startTime":"2023-04-27T13:29:15.595-05:00[America/Bogota]","result":"SUCCESS","restQuery":{"method":"POST","path":"https://campus-matcafe-backend-sofka-production.up.railway.app/learner/subscribeRoute\r","content":"{\n    \"routeid\": \"644ab5633204e8c1f59f3215\",\n    \"learnedId\": \"6447512d8cc268d0e07e4d40\"\n}\r","contentType":"application/json","requestHeaders":"Accept\u003d*/*\r\n\t\t\t\tContent-Type\u003dapplication/json; charset\u003dUTF-8\r","requestCookies":"\r","responseHeaders":"x-powered-by: Express\r\naccess-control-allow-origin: *\r\ncontent-type: text/html; charset\u003dutf-8\r\ncontent-length: 27\r\netag: W/\"1b-OCiv7kO02FuXp83ZMTcQbKFtsjI\"\r\ndate: Thu, 27 Apr 2023 18:29:15 GMT\r\nserver: railway\r","responseCookies":"\r","responseBody":"\u003chtml\u003e\n  \u003cbody\u003eRuta agregada correctamente\u003c/body\u003e\n\u003c/html\u003e","statusCode":201},"precondition":false,"level":4}]}]}]},{"number":7,"description":"Then se inscribe el aprendiz a la ruta y se muestra un esatatus 201","duration":7,"startTime":"2023-04-27T13:29:15.601-05:00[America/Bogota]","result":"SUCCESS","precondition":false,"level":1,"children":[{"number":8,"description":"Se debe mostrar el  estatus correspondiente","duration":0,"startTime":"2023-04-27T13:29:15.603-05:00[America/Bogota]","result":"SUCCESS","precondition":false,"level":2},{"number":9,"description":"El cuerpo de respuesta no debe ser nulo","duration":2,"startTime":"2023-04-27T13:29:15.604-05:00[America/Bogota]","result":"SUCCESS","precondition":false,"level":2}]}]},{"number":10,"description":"Example: {learnedId\u003d\"644756609a1062742d432b9e\", courseId\u003d\"644ab5633204e8c1f59f3215\", status\u003d201}","duration":750,"startTime":"2023-04-27T13:29:15.641-05:00[America/Bogota]","result":"SUCCESS","precondition":false,"level":0,"lineNumber":16,"children":[{"number":11,"description":"Given el administrador desea inscribir un aprendiz a una ruta de aprendizaje","duration":6,"startTime":"2023-04-27T13:29:15.646-05:00[America/Bogota]","result":"SUCCESS","precondition":false,"level":1},{"number":12,"description":"When envia el reto con los datos de  id del aprendiz \"644756609a1062742d432b9e\" y  id del curso \"644ab5633204e8c1f59f3215\"","duration":728,"startTime":"2023-04-27T13:29:15.654-05:00[America/Bogota]","result":"SUCCESS","precondition":false,"level":1,"children":[{"number":13,"description":"Team2 do post","duration":722,"startTime":"2023-04-27T13:29:15.658-05:00[America/Bogota]","result":"SUCCESS","precondition":false,"level":2,"children":[{"number":14,"description":"team2 executes a POST on the resource learner/subscribeRoute","duration":718,"startTime":"2023-04-27T13:29:15.662-05:00[America/Bogota]","result":"SUCCESS","precondition":false,"level":3,"children":[{"number":15,"description":"POST https://campus-matcafe-backend-sofka-production.up.railway.app/learner/subscribeRoute\r","duration":0,"startTime":"2023-04-27T13:29:16.380-05:00[America/Bogota]","result":"SUCCESS","restQuery":{"method":"POST","path":"https://campus-matcafe-backend-sofka-production.up.railway.app/learner/subscribeRoute\r","content":"{\n    \"routeid\": \"644ab5633204e8c1f59f3215\",\n    \"learnedId\": \"644756609a1062742d432b9e\"\n}\r","contentType":"application/json","requestHeaders":"Accept\u003d*/*\r\n\t\t\t\tContent-Type\u003dapplication/json; charset\u003dUTF-8\r","requestCookies":"\r","responseHeaders":"x-powered-by: Express\r\naccess-control-allow-origin: *\r\ncontent-type: text/html; charset\u003dutf-8\r\ncontent-length: 27\r\netag: W/\"1b-OCiv7kO02FuXp83ZMTcQbKFtsjI\"\r\ndate: Thu, 27 Apr 2023 18:29:16 GMT\r\nserver: railway\r","responseCookies":"\r","responseBody":"\u003chtml\u003e\n  \u003cbody\u003eRuta agregada correctamente\u003c/body\u003e\n\u003c/html\u003e","statusCode":201},"precondition":false,"level":4}]}]}]},{"number":16,"description":"Then se inscribe el aprendiz a la ruta y se muestra un esatatus 201","duration":5,"startTime":"2023-04-27T13:29:16.385-05:00[America/Bogota]","result":"SUCCESS","precondition":false,"level":1,"children":[{"number":17,"description":"Se debe mostrar el  estatus correspondiente","duration":1,"startTime":"2023-04-27T13:29:16.386-05:00[America/Bogota]","result":"SUCCESS","precondition":false,"level":2},{"number":18,"description":"El cuerpo de respuesta no debe ser nulo","duration":1,"startTime":"2023-04-27T13:29:16.387-05:00[America/Bogota]","result":"SUCCESS","precondition":false,"level":2}]}]}],"userStory":{"id":"inscribir-aprendices-a-rutas-de-aprendizaje","storyName":"Inscribir aprendices a rutas de aprendizaje","path":"file:///C:/Users/nunez/Escritorio/Automatizacion%20final/AutomatizacionBackendMatCafe/src/test/resources/features/HUB13inscripcionaunaruta.feature","narrative":"  Yo como administrador de la web Campus\n  Quiero inscribir aprendices a distintas rutas de aprendizaje\n  Para gestionar el aprendizaje de los aprendices","type":"feature"},"featureTag":{"name":"Features/Inscribir aprendices a rutas de aprendizaje","type":"feature","displayName":"Features/Inscribir aprendices a rutas de aprendizaje"},"title":"Inscribir aprendices en una ruta de manera exitosa","tags":[{"name":"InscribirAprendicesEnUnaRutaDeManeraExitosa","type":"tag","displayName":"InscribirAprendicesEnUnaRutaDeManeraExitosa"},{"name":"Inscribir aprendices a rutas de aprendizaje","type":"feature","displayName":"Inscribir aprendices a rutas de aprendizaje"}],"startTime":"2023-04-27T13:29:14.853-05:00[America/Bogota]","duration":1539,"projectKey":"","isManualTestingUpToDate":false,"dataTable":{"headers":["learnedId","courseId","status"],"rows":[{"values":["\"6447512d8cc268d0e07e4d40\"","\"644ab5633204e8c1f59f3215\"","201"],"lineNumber":15,"result":"SUCCESS"},{"values":["\"644756609a1062742d432b9e\"","\"644ab5633204e8c1f59f3215\"","201"],"lineNumber":16,"result":"SUCCESS"}],"predefinedRows":true,"scenarioOutline":"Given el administrador desea inscribir un aprendiz a una ruta de aprendizaje\n\rWhen envia el reto con los datos de  id del aprendiz \u003clearnedId\u003e y  id del curso \u003ccourseId\u003e\n\rThen se inscribe el aprendiz a la ruta y se muestra un esatatus \u003cstatus\u003e\n\r","dataSetDescriptors":[{"startRow":0,"rowCount":0,"name":""}]},"manual":false,"testSource":"Cucumber","actors":[{"name":"team2","can":["call an API at https://campus-matcafe-backend-sofka-production.up.railway.app/"]}],"result":"SUCCESS","scenarioOutline":"Given el administrador desea inscribir un aprendiz a una ruta de aprendizaje\r\nWhen envia el reto con los datos de  id del aprendiz \u003clearnedId\u003e y  id del curso \u003ccourseId\u003e\r\nThen se inscribe el aprendiz a la ruta y se muestra un esatatus \u003cstatus\u003e"}